odoo/addons/account_avatax_website_sale/README.rst
odoo/addons/account_avatax_website_sale/__init__.py
odoo/addons/account_avatax_website_sale/__manifest__.py
odoo/addons/account_avatax_website_sale/controllers/__init__.py
odoo/addons/account_avatax_website_sale/controllers/main.py
odoo/addons/account_avatax_website_sale/i18n/account_avatax_website_sale.pot
odoo/addons/account_avatax_website_sale/i18n/it.po
odoo/addons/account_avatax_website_sale/readme/CONTRIBUTORS.md
odoo/addons/account_avatax_website_sale/readme/DESCRIPTION.md
odoo/addons/account_avatax_website_sale/readme/USAGE.md
odoo/addons/account_avatax_website_sale/static/description/icon.png
odoo/addons/account_avatax_website_sale/static/description/index.html
odoo_addon_account_avatax_website_sale-18.0.1.0.0.2.dist-info/METADATA
odoo_addon_account_avatax_website_sale-18.0.1.0.0.2.dist-info/WHEEL
odoo_addon_account_avatax_website_sale-18.0.1.0.0.2.dist-info/top_level.txt
odoo_addon_account_avatax_website_sale-18.0.1.0.0.2.dist-info/RECORD
