Metadata-Version: 2.1
Name: odoo-addon-account_avatax_website_sale
Version: 18.0.1.0.0.2
Requires-Python: >=3.10
Requires-Dist: odoo-addon-account_avatax_sale_oca==18.0.*
Requires-Dist: odoo==18.0.*
Summary: Ecommerce Sales Orders require tax recalculation prior to payment.
Home-page: https://github.com/OCA/account-fiscal-rule
License: AGPL-3
Author: Cybernexus Solutions, Odoo Community Association (OCA)
Author-email: support@odoo-community.org
Classifier: Programming Language :: Python
Classifier: Framework :: Odoo
Classifier: Framework :: Odoo :: 18.0
Classifier: License :: OSI Approved :: GNU Affero General Public License v3
Classifier: Development Status :: 4 - Beta
